README.txt
setup.py
boois_mysql_db_helper/__init__.py
boois_mysql_db_helper/mysql_db_helper.py
boois_mysql_db_helper.egg-info/PKG-INFO
boois_mysql_db_helper.egg-info/SOURCES.txt
boois_mysql_db_helper.egg-info/dependency_links.txt
boois_mysql_db_helper.egg-info/top_level.txt
boois_mysql_db_helper.egg-info/zip-safe