Metadata-Version: 1.1
Name: boois-mysql-db-helper
Version: 1.1.0
Summary: boois_mysql_db_helper
Home-page: http://www.boois.cn/
Author: boois
Author-email: admin@boois.cn
License: MIT
Keywords: boois_mysql_db_helper
Platform: UNKNOWN
Classifier: License :: OSI Approved :: MIT License
Classifier: Programming Language :: Python
Classifier: Intended Audience :: Developers
Classifier: Operating System :: OS Independent
